javelin_cli/__init__.py
javelin_cli/__main__.py
javelin_cli/_internal/__init__.py
javelin_cli/_internal/commands.py
javelin_cli/cli.py
javelin_sdk/__init__.py
javelin_sdk/chat_completions.py
javelin_sdk/client.py
javelin_sdk/exceptions.py
javelin_sdk/model_adapters.py
javelin_sdk/models.py
javelin_sdk/services/gateway_service.py
javelin_sdk/services/guardrails_service.py
javelin_sdk/services/modelspec_service.py
javelin_sdk/services/provider_service.py
javelin_sdk/services/route_service.py
javelin_sdk/services/secret_service.py
javelin_sdk/services/template_service.py
javelin_sdk/services/trace_service.py
javelin_sdk/tracing_setup.py
javelin_sdk-0.2.40.dist-info/LICENSE
javelin_sdk-0.2.40.dist-info/METADATA
javelin_sdk-0.2.40.dist-info/WHEEL
javelin_sdk-0.2.40.dist-info/entry_points.txt
javelin_sdk-0.2.40.dist-info/RECORD
