Metadata-Version: 2.3
Name: javelin-sdk
Version: 0.2.40
Summary: Python client for Javelin
License: Apache-2.0
Author: Sharath Rajasekar
Author-email: sharath@getjavelin.com
Requires-Python: >=3.9,<4.0
Classifier: License :: OSI Approved :: Apache Software License
Classifier: Programming Language :: Python :: 3
Classifier: Programming Language :: Python :: 3.9
Classifier: Programming Language :: Python :: 3.10
Classifier: Programming Language :: Python :: 3.11
Classifier: Programming Language :: Python :: 3.12
Classifier: Programming Language :: Python :: 3.13
Requires-Dist: httpx (>=0.27.2,<0.28.0)
Requires-Dist: jmespath (>=1.0.1,<2.0.0)
Requires-Dist: jsonpath-ng (>=1.7.0,<2.0.0)
Requires-Dist: opentelemetry-api (>=1.32.1,<2.0.0)
Requires-Dist: opentelemetry-exporter-otlp-proto-grpc (>=1.32.1,<2.0.0)
Requires-Dist: opentelemetry-exporter-otlp-proto-http (>=1.32.1,<2.0.0)
Requires-Dist: opentelemetry-sdk (>=1.32.1,<2.0.0)
Requires-Dist: opentelemetry-semantic-conventions (>=0.53b1,<0.54)
Requires-Dist: pydantic (>=2.9.2,<3.0.0)
Requires-Dist: requests (>=2.31.0,<3.0.0)
Project-URL: Homepage, https://getjavelin.com
